pibooth_background_changer.py
pibooth_background_changer-1.1.0.dist-info/LICENSE
pibooth_background_changer-1.1.0.dist-info/METADATA
pibooth_background_changer-1.1.0.dist-info/WHEEL
pibooth_background_changer-1.1.0.dist-info/entry_points.txt
pibooth_background_changer-1.1.0.dist-info/top_level.txt
pibooth_background_changer-1.1.0.dist-info/RECORD
