Metadata-Version: 2.1
Name: pibooth-background-changer
Version: 1.1.0
Summary: Pibooth plugin to remove and replace photo backgrounds using AI
Home-page: https://github.com/ceeeeb/pibooth-background-changer
Author: Christophe
License: MIT
Keywords: pibooth photobooth background removal AI rembg
Classifier: Development Status :: 4 - Beta
Classifier: Environment :: Plugins
Classifier: Intended Audience :: End Users/Desktop
Classifier: License :: OSI Approved :: MIT License
Classifier: Operating System :: OS Independent
Classifier: Programming Language :: Python :: 3
Classifier: Programming Language :: Python :: 3.7
Classifier: Programming Language :: Python :: 3.8
Classifier: Programming Language :: Python :: 3.9
Classifier: Programming Language :: Python :: 3.10
Classifier: Programming Language :: Python :: 3.11
Classifier: Topic :: Multimedia :: Graphics
Requires-Python: >=3.7
License-File: LICENSE
Requires-Dist: Pillow >=8.0.0
Requires-Dist: pibooth >=2.0.0
Requires-Dist: rembg >=2.0.0
Provides-Extra: gpu
Requires-Dist: rembg[gpu] >=2.0.0 ; extra == 'gpu'
